cas_schema/__init__.py
cas_schema/catalog.yaml
cas_schema/json_utils.py
cas_schema/schema_docs.py
cas_schema/schema_manager.py
cas_schema/schema_merger.py
cas_schema/schema_validator.py
cas_schema/schemas/BICAN_schema.json
cas_schema/schemas/CAP_schema.json
cas_schema/schemas/__init__.py
cas_schema/schemas/general_schema.json
cell_annotation_schema-1.1.0.dist-info/METADATA
cell_annotation_schema-1.1.0.dist-info/WHEEL
cell_annotation_schema-1.1.0.dist-info/top_level.txt
cell_annotation_schema-1.1.0.dist-info/RECORD
