Metadata-Version: 2.1
Name: cell-annotation-schema
Version: 1.1.0
Summary: Cell Annotation Schema
Home-page: https://github.com/cellannotation/cell-annotation-schema
Author: 
License: Apache-2.0 license
Platform: UNKNOWN
Classifier: Programming Language :: Python :: 3
Classifier: License :: OSI Approved :: GNU General Public License v3 (GPLv3)
Classifier: Operating System :: OS Independent
Requires-Dist: jsonschema==4.4.0
Requires-Dist: ordered-set==4.1.0
Requires-Dist: deepmerge==1.1.0
Requires-Dist: ruamel.yaml
